[
    {
        "arguments": [
            "clang++",
            "-c",
            "-target",
            "armv7ar-none-none-eabi",
            "-fno-ms-extensions",
            "-fno-ms-compatibility",
            "-fno-delayed-template-parsing",
            "-isystemc:\\program files\\pros\\toolchain\\usr\\bin\\../lib/gcc/arm-none-eabi/7.2.1/../../../../arm-none-eabi/include/c++/7.2.1",
            "-isystemc:\\program files\\pros\\toolchain\\usr\\bin\\../lib/gcc/arm-none-eabi/7.2.1/../../../../arm-none-eabi/include/c++/7.2.1/arm-none-eabi/thumb/v7-ar/fpv3/softfp",
            "-isystemc:\\program files\\pros\\toolchain\\usr\\bin\\../lib/gcc/arm-none-eabi/7.2.1/../../../../arm-none-eabi/include/c++/7.2.1/backward",
            "-isystemc:\\program files\\pros\\toolchain\\usr\\bin\\../lib/gcc/arm-none-eabi/7.2.1/include",
            "-isystemc:\\program files\\pros\\toolchain\\usr\\bin\\../lib/gcc/arm-none-eabi/7.2.1/include-fixed",
            "-isystemc:\\program files\\pros\\toolchain\\usr\\bin\\../lib/gcc/arm-none-eabi/7.2.1/../../../../arm-none-eabi/include",
            "-iquote./include",
            "-iquote./include/./",
            "-mcpu=cortex-a9",
            "-mfpu=neon-fp16",
            "-mfloat-abi=softfp",
            "-Os",
            "-g",
            "-D_POSIX_THREADS",
            "-D_UNIX98_THREAD_MUTEX_ATTRIBUTES",
            "-ffunction-sections",
            "-fdata-sections",
            "-fdiagnostics-color",
            "-funwind-tables",
            "--std=gnu++17",
            "-o",
            "C:/Users/Randhawa/AppData/Local/Temp/tmp_88y_l90/autonomous.cpp.o",
            "src\\autonomous.cpp"
        ],
        "directory": "C:\\4549D_Code\\LastChance",
        "file": "src\\autonomous.cpp"
    },
    {
        "arguments": [
            "clang++",
            "-c",
            "-target",
            "armv7ar-none-none-eabi",
            "-fno-ms-extensions",
            "-fno-ms-compatibility",
            "-fno-delayed-template-parsing",
            "-isystemc:\\program files\\pros\\toolchain\\usr\\bin\\../lib/gcc/arm-none-eabi/7.2.1/include",
            "-isystemc:\\program files\\pros\\toolchain\\usr\\bin\\../lib/gcc/arm-none-eabi/7.2.1/include-fixed",
            "-isystemc:\\program files\\pros\\toolchain\\usr\\bin\\../lib/gcc/arm-none-eabi/7.2.1/../../../../arm-none-eabi/include",
            "-iquote./include",
            "-iquote./include/./",
            "-mcpu=cortex-a9",
            "-mfpu=neon-fp16",
            "-mfloat-abi=softfp",
            "-Os",
            "-g",
            "-D_POSIX_THREADS",
            "-D_UNIX98_THREAD_MUTEX_ATTRIBUTES",
            "-ffunction-sections",
            "-fdata-sections",
            "-fdiagnostics-color",
            "-funwind-tables",
            "--std=gnu11",
            "-o",
            "C:/Users/Randhawa/AppData/Local/Temp/tmp_88y_l90/logo.c.o",
            "src\\logo.c"
        ],
        "directory": "C:\\4549D_Code\\LastChance",
        "file": "src\\logo.c"
    },
    {
        "arguments": [
            "clang++",
            "-c",
            "-target",
            "armv7ar-none-none-eabi",
            "-fno-ms-extensions",
            "-fno-ms-compatibility",
            "-fno-delayed-template-parsing",
            "-isystemc:\\program files\\pros\\toolchain\\usr\\bin\\../lib/gcc/arm-none-eabi/7.2.1/../../../../arm-none-eabi/include/c++/7.2.1",
            "-isystemc:\\program files\\pros\\toolchain\\usr\\bin\\../lib/gcc/arm-none-eabi/7.2.1/../../../../arm-none-eabi/include/c++/7.2.1/arm-none-eabi/thumb/v7-ar/fpv3/softfp",
            "-isystemc:\\program files\\pros\\toolchain\\usr\\bin\\../lib/gcc/arm-none-eabi/7.2.1/../../../../arm-none-eabi/include/c++/7.2.1/backward",
            "-isystemc:\\program files\\pros\\toolchain\\usr\\bin\\../lib/gcc/arm-none-eabi/7.2.1/include",
            "-isystemc:\\program files\\pros\\toolchain\\usr\\bin\\../lib/gcc/arm-none-eabi/7.2.1/include-fixed",
            "-isystemc:\\program files\\pros\\toolchain\\usr\\bin\\../lib/gcc/arm-none-eabi/7.2.1/../../../../arm-none-eabi/include",
            "-iquote./include",
            "-iquote./include/./",
            "-mcpu=cortex-a9",
            "-mfpu=neon-fp16",
            "-mfloat-abi=softfp",
            "-Os",
            "-g",
            "-D_POSIX_THREADS",
            "-D_UNIX98_THREAD_MUTEX_ATTRIBUTES",
            "-ffunction-sections",
            "-fdata-sections",
            "-fdiagnostics-color",
            "-funwind-tables",
            "--std=gnu++17",
            "-o",
            "C:/Users/Randhawa/AppData/Local/Temp/tmp_88y_l90/lift.cpp.o",
            "src\\lift.cpp"
        ],
        "directory": "C:\\4549D_Code\\LastChance",
        "file": "src\\lift.cpp"
    },
    {
        "arguments": [
            "clang++",
            "-c",
            "-target",
            "armv7ar-none-none-eabi",
            "-fno-ms-extensions",
            "-fno-ms-compatibility",
            "-fno-delayed-template-parsing",
            "-isystemc:\\program files\\pros\\toolchain\\usr\\bin\\../lib/gcc/arm-none-eabi/7.2.1/../../../../arm-none-eabi/include/c++/7.2.1",
            "-isystemc:\\program files\\pros\\toolchain\\usr\\bin\\../lib/gcc/arm-none-eabi/7.2.1/../../../../arm-none-eabi/include/c++/7.2.1/arm-none-eabi/thumb/v7-ar/fpv3/softfp",
            "-isystemc:\\program files\\pros\\toolchain\\usr\\bin\\../lib/gcc/arm-none-eabi/7.2.1/../../../../arm-none-eabi/include/c++/7.2.1/backward",
            "-isystemc:\\program files\\pros\\toolchain\\usr\\bin\\../lib/gcc/arm-none-eabi/7.2.1/include",
            "-isystemc:\\program files\\pros\\toolchain\\usr\\bin\\../lib/gcc/arm-none-eabi/7.2.1/include-fixed",
            "-isystemc:\\program files\\pros\\toolchain\\usr\\bin\\../lib/gcc/arm-none-eabi/7.2.1/../../../../arm-none-eabi/include",
            "-iquote./include",
            "-iquote./include/./",
            "-mcpu=cortex-a9",
            "-mfpu=neon-fp16",
            "-mfloat-abi=softfp",
            "-Os",
            "-g",
            "-D_POSIX_THREADS",
            "-D_UNIX98_THREAD_MUTEX_ATTRIBUTES",
            "-ffunction-sections",
            "-fdata-sections",
            "-fdiagnostics-color",
            "-funwind-tables",
            "--std=gnu++17",
            "-o",
            "C:/Users/Randhawa/AppData/Local/Temp/tmp_88y_l90/auto_drive.cpp.o",
            "src\\auto_drive.cpp"
        ],
        "directory": "C:\\4549D_Code\\LastChance",
        "file": "src\\auto_drive.cpp"
    },
    {
        "arguments": [
            "clang++",
            "-c",
            "-target",
            "armv7ar-none-none-eabi",
            "-fno-ms-extensions",
            "-fno-ms-compatibility",
            "-fno-delayed-template-parsing",
            "-isystemc:\\program files\\pros\\toolchain\\usr\\bin\\../lib/gcc/arm-none-eabi/7.2.1/../../../../arm-none-eabi/include/c++/7.2.1",
            "-isystemc:\\program files\\pros\\toolchain\\usr\\bin\\../lib/gcc/arm-none-eabi/7.2.1/../../../../arm-none-eabi/include/c++/7.2.1/arm-none-eabi/thumb/v7-ar/fpv3/softfp",
            "-isystemc:\\program files\\pros\\toolchain\\usr\\bin\\../lib/gcc/arm-none-eabi/7.2.1/../../../../arm-none-eabi/include/c++/7.2.1/backward",
            "-isystemc:\\program files\\pros\\toolchain\\usr\\bin\\../lib/gcc/arm-none-eabi/7.2.1/include",
            "-isystemc:\\program files\\pros\\toolchain\\usr\\bin\\../lib/gcc/arm-none-eabi/7.2.1/include-fixed",
            "-isystemc:\\program files\\pros\\toolchain\\usr\\bin\\../lib/gcc/arm-none-eabi/7.2.1/../../../../arm-none-eabi/include",
            "-iquote./include",
            "-iquote./include/./",
            "-mcpu=cortex-a9",
            "-mfpu=neon-fp16",
            "-mfloat-abi=softfp",
            "-Os",
            "-g",
            "-D_POSIX_THREADS",
            "-D_UNIX98_THREAD_MUTEX_ATTRIBUTES",
            "-ffunction-sections",
            "-fdata-sections",
            "-fdiagnostics-color",
            "-funwind-tables",
            "--std=gnu++17",
            "-o",
            "C:/Users/Randhawa/AppData/Local/Temp/tmp_88y_l90/main.cpp.o",
            "src\\main.cpp"
        ],
        "directory": "C:\\4549D_Code\\LastChance",
        "file": "src\\main.cpp"
    },
    {
        "arguments": [
            "clang++",
            "-c",
            "-target",
            "armv7ar-none-none-eabi",
            "-fno-ms-extensions",
            "-fno-ms-compatibility",
            "-fno-delayed-template-parsing",
            "-isystemc:\\program files\\pros\\toolchain\\usr\\bin\\../lib/gcc/arm-none-eabi/7.2.1/../../../../arm-none-eabi/include/c++/7.2.1",
            "-isystemc:\\program files\\pros\\toolchain\\usr\\bin\\../lib/gcc/arm-none-eabi/7.2.1/../../../../arm-none-eabi/include/c++/7.2.1/arm-none-eabi/thumb/v7-ar/fpv3/softfp",
            "-isystemc:\\program files\\pros\\toolchain\\usr\\bin\\../lib/gcc/arm-none-eabi/7.2.1/../../../../arm-none-eabi/include/c++/7.2.1/backward",
            "-isystemc:\\program files\\pros\\toolchain\\usr\\bin\\../lib/gcc/arm-none-eabi/7.2.1/include",
            "-isystemc:\\program files\\pros\\toolchain\\usr\\bin\\../lib/gcc/arm-none-eabi/7.2.1/include-fixed",
            "-isystemc:\\program files\\pros\\toolchain\\usr\\bin\\../lib/gcc/arm-none-eabi/7.2.1/../../../../arm-none-eabi/include",
            "-iquote./include",
            "-iquote./include/./",
            "-mcpu=cortex-a9",
            "-mfpu=neon-fp16",
            "-mfloat-abi=softfp",
            "-Os",
            "-g",
            "-D_POSIX_THREADS",
            "-D_UNIX98_THREAD_MUTEX_ATTRIBUTES",
            "-ffunction-sections",
            "-fdata-sections",
            "-fdiagnostics-color",
            "-funwind-tables",
            "--std=gnu++17",
            "-o",
            "C:/Users/Randhawa/AppData/Local/Temp/tmp_88y_l90/odometry.cpp.o",
            "src\\odometry.cpp"
        ],
        "directory": "C:\\4549D_Code\\LastChance",
        "file": "src\\odometry.cpp"
    },
    {
        "arguments": [
            "clang++",
            "-c",
            "-target",
            "armv7ar-none-none-eabi",
            "-fno-ms-extensions",
            "-fno-ms-compatibility",
            "-fno-delayed-template-parsing",
            "-isystemc:\\program files\\pros\\toolchain\\usr\\bin\\../lib/gcc/arm-none-eabi/7.2.1/../../../../arm-none-eabi/include/c++/7.2.1",
            "-isystemc:\\program files\\pros\\toolchain\\usr\\bin\\../lib/gcc/arm-none-eabi/7.2.1/../../../../arm-none-eabi/include/c++/7.2.1/arm-none-eabi/thumb/v7-ar/fpv3/softfp",
            "-isystemc:\\program files\\pros\\toolchain\\usr\\bin\\../lib/gcc/arm-none-eabi/7.2.1/../../../../arm-none-eabi/include/c++/7.2.1/backward",
            "-isystemc:\\program files\\pros\\toolchain\\usr\\bin\\../lib/gcc/arm-none-eabi/7.2.1/include",
            "-isystemc:\\program files\\pros\\toolchain\\usr\\bin\\../lib/gcc/arm-none-eabi/7.2.1/include-fixed",
            "-isystemc:\\program files\\pros\\toolchain\\usr\\bin\\../lib/gcc/arm-none-eabi/7.2.1/../../../../arm-none-eabi/include",
            "-iquote./include",
            "-iquote./include/./",
            "-mcpu=cortex-a9",
            "-mfpu=neon-fp16",
            "-mfloat-abi=softfp",
            "-Os",
            "-g",
            "-D_POSIX_THREADS",
            "-D_UNIX98_THREAD_MUTEX_ATTRIBUTES",
            "-ffunction-sections",
            "-fdata-sections",
            "-fdiagnostics-color",
            "-funwind-tables",
            "--std=gnu++17",
            "-o",
            "C:/Users/Randhawa/AppData/Local/Temp/tmp_88y_l90/utilities.cpp.o",
            "src\\utilities.cpp"
        ],
        "directory": "C:\\4549D_Code\\LastChance",
        "file": "src\\utilities.cpp"
    },
    {
        "arguments": [
            "clang++",
            "-c",
            "-target",
            "armv7ar-none-none-eabi",
            "-fno-ms-extensions",
            "-fno-ms-compatibility",
            "-fno-delayed-template-parsing",
            "-isystemc:\\program files\\pros\\toolchain\\usr\\bin\\../lib/gcc/arm-none-eabi/7.2.1/../../../../arm-none-eabi/include/c++/7.2.1",
            "-isystemc:\\program files\\pros\\toolchain\\usr\\bin\\../lib/gcc/arm-none-eabi/7.2.1/../../../../arm-none-eabi/include/c++/7.2.1/arm-none-eabi/thumb/v7-ar/fpv3/softfp",
            "-isystemc:\\program files\\pros\\toolchain\\usr\\bin\\../lib/gcc/arm-none-eabi/7.2.1/../../../../arm-none-eabi/include/c++/7.2.1/backward",
            "-isystemc:\\program files\\pros\\toolchain\\usr\\bin\\../lib/gcc/arm-none-eabi/7.2.1/include",
            "-isystemc:\\program files\\pros\\toolchain\\usr\\bin\\../lib/gcc/arm-none-eabi/7.2.1/include-fixed",
            "-isystemc:\\program files\\pros\\toolchain\\usr\\bin\\../lib/gcc/arm-none-eabi/7.2.1/../../../../arm-none-eabi/include",
            "-iquote./include",
            "-iquote./include/./",
            "-mcpu=cortex-a9",
            "-mfpu=neon-fp16",
            "-mfloat-abi=softfp",
            "-Os",
            "-g",
            "-D_POSIX_THREADS",
            "-D_UNIX98_THREAD_MUTEX_ATTRIBUTES",
            "-ffunction-sections",
            "-fdata-sections",
            "-fdiagnostics-color",
            "-funwind-tables",
            "--std=gnu++17",
            "-o",
            "C:/Users/Randhawa/AppData/Local/Temp/tmp_88y_l90/motors.cpp.o",
            "src\\motors.cpp"
        ],
        "directory": "C:\\4549D_Code\\LastChance",
        "file": "src\\motors.cpp"
    },
    {
        "arguments": [
            "clang++",
            "-c",
            "-target",
            "armv7ar-none-none-eabi",
            "-fno-ms-extensions",
            "-fno-ms-compatibility",
            "-fno-delayed-template-parsing",
            "-isystemc:\\program files\\pros\\toolchain\\usr\\bin\\../lib/gcc/arm-none-eabi/7.2.1/../../../../arm-none-eabi/include/c++/7.2.1",
            "-isystemc:\\program files\\pros\\toolchain\\usr\\bin\\../lib/gcc/arm-none-eabi/7.2.1/../../../../arm-none-eabi/include/c++/7.2.1/arm-none-eabi/thumb/v7-ar/fpv3/softfp",
            "-isystemc:\\program files\\pros\\toolchain\\usr\\bin\\../lib/gcc/arm-none-eabi/7.2.1/../../../../arm-none-eabi/include/c++/7.2.1/backward",
            "-isystemc:\\program files\\pros\\toolchain\\usr\\bin\\../lib/gcc/arm-none-eabi/7.2.1/include",
            "-isystemc:\\program files\\pros\\toolchain\\usr\\bin\\../lib/gcc/arm-none-eabi/7.2.1/include-fixed",
            "-isystemc:\\program files\\pros\\toolchain\\usr\\bin\\../lib/gcc/arm-none-eabi/7.2.1/../../../../arm-none-eabi/include",
            "-iquote./include",
            "-iquote./include/./",
            "-mcpu=cortex-a9",
            "-mfpu=neon-fp16",
            "-mfloat-abi=softfp",
            "-Os",
            "-g",
            "-D_POSIX_THREADS",
            "-D_UNIX98_THREAD_MUTEX_ATTRIBUTES",
            "-ffunction-sections",
            "-fdata-sections",
            "-fdiagnostics-color",
            "-funwind-tables",
            "--std=gnu++17",
            "-o",
            "C:/Users/Randhawa/AppData/Local/Temp/tmp_88y_l90/controller_printing.cpp.o",
            "src\\controller_printing.cpp"
        ],
        "directory": "C:\\4549D_Code\\LastChance",
        "file": "src\\controller_printing.cpp"
    },
    {
        "arguments": [
            "clang++",
            "-c",
            "-target",
            "armv7ar-none-none-eabi",
            "-fno-ms-extensions",
            "-fno-ms-compatibility",
            "-fno-delayed-template-parsing",
            "-isystemc:\\program files\\pros\\toolchain\\usr\\bin\\../lib/gcc/arm-none-eabi/7.2.1/../../../../arm-none-eabi/include/c++/7.2.1",
            "-isystemc:\\program files\\pros\\toolchain\\usr\\bin\\../lib/gcc/arm-none-eabi/7.2.1/../../../../arm-none-eabi/include/c++/7.2.1/arm-none-eabi/thumb/v7-ar/fpv3/softfp",
            "-isystemc:\\program files\\pros\\toolchain\\usr\\bin\\../lib/gcc/arm-none-eabi/7.2.1/../../../../arm-none-eabi/include/c++/7.2.1/backward",
            "-isystemc:\\program files\\pros\\toolchain\\usr\\bin\\../lib/gcc/arm-none-eabi/7.2.1/include",
            "-isystemc:\\program files\\pros\\toolchain\\usr\\bin\\../lib/gcc/arm-none-eabi/7.2.1/include-fixed",
            "-isystemc:\\program files\\pros\\toolchain\\usr\\bin\\../lib/gcc/arm-none-eabi/7.2.1/../../../../arm-none-eabi/include",
            "-iquote./include",
            "-iquote./include/./",
            "-mcpu=cortex-a9",
            "-mfpu=neon-fp16",
            "-mfloat-abi=softfp",
            "-Os",
            "-g",
            "-D_POSIX_THREADS",
            "-D_UNIX98_THREAD_MUTEX_ATTRIBUTES",
            "-ffunction-sections",
            "-fdata-sections",
            "-fdiagnostics-color",
            "-funwind-tables",
            "--std=gnu++17",
            "-o",
            "C:/Users/Randhawa/AppData/Local/Temp/tmp_88y_l90/sensors.cpp.o",
            "src\\sensors.cpp"
        ],
        "directory": "C:\\4549D_Code\\LastChance",
        "file": "src\\sensors.cpp"
    },
    {
        "arguments": [
            "clang++",
            "-c",
            "-target",
            "armv7ar-none-none-eabi",
            "-fno-ms-extensions",
            "-fno-ms-compatibility",
            "-fno-delayed-template-parsing",
            "-isystemc:\\program files\\pros\\toolchain\\usr\\bin\\../lib/gcc/arm-none-eabi/7.2.1/../../../../arm-none-eabi/include/c++/7.2.1",
            "-isystemc:\\program files\\pros\\toolchain\\usr\\bin\\../lib/gcc/arm-none-eabi/7.2.1/../../../../arm-none-eabi/include/c++/7.2.1/arm-none-eabi/thumb/v7-ar/fpv3/softfp",
            "-isystemc:\\program files\\pros\\toolchain\\usr\\bin\\../lib/gcc/arm-none-eabi/7.2.1/../../../../arm-none-eabi/include/c++/7.2.1/backward",
            "-isystemc:\\program files\\pros\\toolchain\\usr\\bin\\../lib/gcc/arm-none-eabi/7.2.1/include",
            "-isystemc:\\program files\\pros\\toolchain\\usr\\bin\\../lib/gcc/arm-none-eabi/7.2.1/include-fixed",
            "-isystemc:\\program files\\pros\\toolchain\\usr\\bin\\../lib/gcc/arm-none-eabi/7.2.1/../../../../arm-none-eabi/include",
            "-iquote./include",
            "-iquote./include/./",
            "-mcpu=cortex-a9",
            "-mfpu=neon-fp16",
            "-mfloat-abi=softfp",
            "-Os",
            "-g",
            "-D_POSIX_THREADS",
            "-D_UNIX98_THREAD_MUTEX_ATTRIBUTES",
            "-ffunction-sections",
            "-fdata-sections",
            "-fdiagnostics-color",
            "-funwind-tables",
            "--std=gnu++17",
            "-o",
            "C:/Users/Randhawa/AppData/Local/Temp/tmp_88y_l90/lcd.cpp.o",
            "src\\lcd.cpp"
        ],
        "directory": "C:\\4549D_Code\\LastChance",
        "file": "src\\lcd.cpp"
    },
    {
        "arguments": [
            "clang++",
            "-c",
            "-target",
            "armv7ar-none-none-eabi",
            "-fno-ms-extensions",
            "-fno-ms-compatibility",
            "-fno-delayed-template-parsing",
            "-isystemc:\\program files\\pros\\toolchain\\usr\\bin\\../lib/gcc/arm-none-eabi/7.2.1/../../../../arm-none-eabi/include/c++/7.2.1",
            "-isystemc:\\program files\\pros\\toolchain\\usr\\bin\\../lib/gcc/arm-none-eabi/7.2.1/../../../../arm-none-eabi/include/c++/7.2.1/arm-none-eabi/thumb/v7-ar/fpv3/softfp",
            "-isystemc:\\program files\\pros\\toolchain\\usr\\bin\\../lib/gcc/arm-none-eabi/7.2.1/../../../../arm-none-eabi/include/c++/7.2.1/backward",
            "-isystemc:\\program files\\pros\\toolchain\\usr\\bin\\../lib/gcc/arm-none-eabi/7.2.1/include",
            "-isystemc:\\program files\\pros\\toolchain\\usr\\bin\\../lib/gcc/arm-none-eabi/7.2.1/include-fixed",
            "-isystemc:\\program files\\pros\\toolchain\\usr\\bin\\../lib/gcc/arm-none-eabi/7.2.1/../../../../arm-none-eabi/include",
            "-iquote./include",
            "-iquote./include/./",
            "-mcpu=cortex-a9",
            "-mfpu=neon-fp16",
            "-mfloat-abi=softfp",
            "-Os",
            "-g",
            "-D_POSIX_THREADS",
            "-D_UNIX98_THREAD_MUTEX_ATTRIBUTES",
            "-ffunction-sections",
            "-fdata-sections",
            "-fdiagnostics-color",
            "-funwind-tables",
            "--std=gnu++17",
            "-o",
            "C:/Users/Randhawa/AppData/Local/Temp/tmp_88y_l90/intake.cpp.o",
            "src\\intake.cpp"
        ],
        "directory": "C:\\4549D_Code\\LastChance",
        "file": "src\\intake.cpp"
    },
    {
        "arguments": [
            "clang++",
            "-c",
            "-target",
            "armv7ar-none-none-eabi",
            "-fno-ms-extensions",
            "-fno-ms-compatibility",
            "-fno-delayed-template-parsing",
            "-isystemc:\\program files\\pros\\toolchain\\usr\\bin\\../lib/gcc/arm-none-eabi/7.2.1/../../../../arm-none-eabi/include/c++/7.2.1",
            "-isystemc:\\program files\\pros\\toolchain\\usr\\bin\\../lib/gcc/arm-none-eabi/7.2.1/../../../../arm-none-eabi/include/c++/7.2.1/arm-none-eabi/thumb/v7-ar/fpv3/softfp",
            "-isystemc:\\program files\\pros\\toolchain\\usr\\bin\\../lib/gcc/arm-none-eabi/7.2.1/../../../../arm-none-eabi/include/c++/7.2.1/backward",
            "-isystemc:\\program files\\pros\\toolchain\\usr\\bin\\../lib/gcc/arm-none-eabi/7.2.1/include",
            "-isystemc:\\program files\\pros\\toolchain\\usr\\bin\\../lib/gcc/arm-none-eabi/7.2.1/include-fixed",
            "-isystemc:\\program files\\pros\\toolchain\\usr\\bin\\../lib/gcc/arm-none-eabi/7.2.1/../../../../arm-none-eabi/include",
            "-iquote./include",
            "-iquote./include/./",
            "-mcpu=cortex-a9",
            "-mfpu=neon-fp16",
            "-mfloat-abi=softfp",
            "-Os",
            "-g",
            "-D_POSIX_THREADS",
            "-D_UNIX98_THREAD_MUTEX_ATTRIBUTES",
            "-ffunction-sections",
            "-fdata-sections",
            "-fdiagnostics-color",
            "-funwind-tables",
            "--std=gnu++17",
            "-o",
            "C:/Users/Randhawa/AppData/Local/Temp/tmp_88y_l90/tilter.cpp.o",
            "src\\tilter.cpp"
        ],
        "directory": "C:\\4549D_Code\\LastChance",
        "file": "src\\tilter.cpp"
    },
    {
        "arguments": [
            "clang++",
            "-c",
            "-target",
            "armv7ar-none-none-eabi",
            "-fno-ms-extensions",
            "-fno-ms-compatibility",
            "-fno-delayed-template-parsing",
            "-isystemc:\\program files\\pros\\toolchain\\usr\\bin\\../lib/gcc/arm-none-eabi/7.2.1/../../../../arm-none-eabi/include/c++/7.2.1",
            "-isystemc:\\program files\\pros\\toolchain\\usr\\bin\\../lib/gcc/arm-none-eabi/7.2.1/../../../../arm-none-eabi/include/c++/7.2.1/arm-none-eabi/thumb/v7-ar/fpv3/softfp",
            "-isystemc:\\program files\\pros\\toolchain\\usr\\bin\\../lib/gcc/arm-none-eabi/7.2.1/../../../../arm-none-eabi/include/c++/7.2.1/backward",
            "-isystemc:\\program files\\pros\\toolchain\\usr\\bin\\../lib/gcc/arm-none-eabi/7.2.1/include",
            "-isystemc:\\program files\\pros\\toolchain\\usr\\bin\\../lib/gcc/arm-none-eabi/7.2.1/include-fixed",
            "-isystemc:\\program files\\pros\\toolchain\\usr\\bin\\../lib/gcc/arm-none-eabi/7.2.1/../../../../arm-none-eabi/include",
            "-iquote./include",
            "-iquote./include/./",
            "-mcpu=cortex-a9",
            "-mfpu=neon-fp16",
            "-mfloat-abi=softfp",
            "-Os",
            "-g",
            "-D_POSIX_THREADS",
            "-D_UNIX98_THREAD_MUTEX_ATTRIBUTES",
            "-ffunction-sections",
            "-fdata-sections",
            "-fdiagnostics-color",
            "-funwind-tables",
            "--std=gnu++17",
            "-o",
            "C:/Users/Randhawa/AppData/Local/Temp/tmp_88y_l90/joystick.cpp.o",
            "src\\joystick.cpp"
        ],
        "directory": "C:\\4549D_Code\\LastChance",
        "file": "src\\joystick.cpp"
    },
    {
        "arguments": [
            "clang++",
            "-c",
            "-target",
            "armv7ar-none-none-eabi",
            "-fno-ms-extensions",
            "-fno-ms-compatibility",
            "-fno-delayed-template-parsing",
            "-isystemc:\\program files\\pros\\toolchain\\usr\\bin\\../lib/gcc/arm-none-eabi/7.2.1/../../../../arm-none-eabi/include/c++/7.2.1",
            "-isystemc:\\program files\\pros\\toolchain\\usr\\bin\\../lib/gcc/arm-none-eabi/7.2.1/../../../../arm-none-eabi/include/c++/7.2.1/arm-none-eabi/thumb/v7-ar/fpv3/softfp",
            "-isystemc:\\program files\\pros\\toolchain\\usr\\bin\\../lib/gcc/arm-none-eabi/7.2.1/../../../../arm-none-eabi/include/c++/7.2.1/backward",
            "-isystemc:\\program files\\pros\\toolchain\\usr\\bin\\../lib/gcc/arm-none-eabi/7.2.1/include",
            "-isystemc:\\program files\\pros\\toolchain\\usr\\bin\\../lib/gcc/arm-none-eabi/7.2.1/include-fixed",
            "-isystemc:\\program files\\pros\\toolchain\\usr\\bin\\../lib/gcc/arm-none-eabi/7.2.1/../../../../arm-none-eabi/include",
            "-iquote./include",
            "-iquote./include/./",
            "-mcpu=cortex-a9",
            "-mfpu=neon-fp16",
            "-mfloat-abi=softfp",
            "-Os",
            "-g",
            "-D_POSIX_THREADS",
            "-D_UNIX98_THREAD_MUTEX_ATTRIBUTES",
            "-ffunction-sections",
            "-fdata-sections",
            "-fdiagnostics-color",
            "-funwind-tables",
            "--std=gnu++17",
            "-o",
            "C:/Users/Randhawa/AppData/Local/Temp/tmp_88y_l90/gui.cpp.o",
            "src\\gui.cpp"
        ],
        "directory": "C:\\4549D_Code\\LastChance",
        "file": "src\\gui.cpp"
    },
    {
        "arguments": [
            "clang++",
            "-c",
            "-target",
            "armv7ar-none-none-eabi",
            "-fno-ms-extensions",
            "-fno-ms-compatibility",
            "-fno-delayed-template-parsing",
            "-isystemc:\\program files\\pros\\toolchain\\usr\\bin\\../lib/gcc/arm-none-eabi/7.2.1/../../../../arm-none-eabi/include/c++/7.2.1",
            "-isystemc:\\program files\\pros\\toolchain\\usr\\bin\\../lib/gcc/arm-none-eabi/7.2.1/../../../../arm-none-eabi/include/c++/7.2.1/arm-none-eabi/thumb/v7-ar/fpv3/softfp",
            "-isystemc:\\program files\\pros\\toolchain\\usr\\bin\\../lib/gcc/arm-none-eabi/7.2.1/../../../../arm-none-eabi/include/c++/7.2.1/backward",
            "-isystemc:\\program files\\pros\\toolchain\\usr\\bin\\../lib/gcc/arm-none-eabi/7.2.1/include",
            "-isystemc:\\program files\\pros\\toolchain\\usr\\bin\\../lib/gcc/arm-none-eabi/7.2.1/include-fixed",
            "-isystemc:\\program files\\pros\\toolchain\\usr\\bin\\../lib/gcc/arm-none-eabi/7.2.1/../../../../arm-none-eabi/include",
            "-iquote./include",
            "-iquote./include/./",
            "-mcpu=cortex-a9",
            "-mfpu=neon-fp16",
            "-mfloat-abi=softfp",
            "-Os",
            "-g",
            "-D_POSIX_THREADS",
            "-D_UNIX98_THREAD_MUTEX_ATTRIBUTES",
            "-ffunction-sections",
            "-fdata-sections",
            "-fdiagnostics-color",
            "-funwind-tables",
            "--std=gnu++17",
            "-o",
            "C:/Users/Randhawa/AppData/Local/Temp/tmp_88y_l90/PID.cpp.o",
            "src\\PID.cpp"
        ],
        "directory": "C:\\4549D_Code\\LastChance",
        "file": "src\\PID.cpp"
    }
]